thcrdt/__init__.py
thcrdt/thcrdt.py
thcrdt/unwrap.py
thcrdt-0.9.2.dist-info/LICENSE
thcrdt-0.9.2.dist-info/WHEEL
thcrdt-0.9.2.dist-info/METADATA
thcrdt-0.9.2.dist-info/RECORD
