Metadata-Version: 2.1
Name: thcrdt
Version: 0.9.2
Summary: TangledHub Thcrdt Library
Home-page: https://gitlab.com/tangledlabs/thcrdt
License: BSD 3-clause
Keywords: tangled,tangledlabs,tangledhub,thcrdt
Author: TangledHub
Author-email: info@tangledgroup.com
Requires-Python: >=3.10,<4.0
Classifier: Development Status :: 4 - Beta
Classifier: Intended Audience :: Developers
Classifier: License :: OSI Approved :: BSD License
Classifier: License :: Other/Proprietary License
Classifier: Operating System :: OS Independent
Classifier: Programming Language :: Python
Classifier: Programming Language :: Python :: 3
Classifier: Programming Language :: Python :: 3.10
Classifier: Programming Language :: Python :: 3.11
Classifier: Programming Language :: Python :: 3.10
Classifier: Programming Language :: Python :: 3.11
Classifier: Topic :: Software Development :: Libraries :: Python Modules
Requires-Dist: thquickjs (>=0.9.0,<0.10.0)
Requires-Dist: thresult (>=0.9.0,<0.10.0)
Project-URL: Repository, https://gitlab.com/tangledlabs/thcrdt
